datahabit/__init__.py
datahabit/behavior_analyzer.py
datahabit/data_cleaner.py
datahabit/deadline_predictor.py
datahabit/difficulty_estimator.py
datahabit/habit_score.py
datahabit/pattern_detector.py
datahabit/report_generator.py
datahabit/task_data.py
datahabit/visualizer.py
datahabit-0.1.1.dist-info/licenses/LICENSE
datahabit-0.1.1.dist-info/METADATA
datahabit-0.1.1.dist-info/WHEEL
datahabit-0.1.1.dist-info/top_level.txt
datahabit-0.1.1.dist-info/RECORD
