Metadata-Version: 2.4
Name: datahabit
Version: 0.1.1
Summary: A Python library designed to analyze academic behavior and productivity patterns based on students’ task timestamps.
Author: Dahe, Aira Grettel C., Dellosa, Karylle L., Hayag, Carmel Marianne T., Java, Armisty Genia L., Trillo, Rodney G.
License: MIT License
Project-URL: Homepage, https://github.com/MUCHIEBERRY/DataHabit
Project-URL: Repository, https://github.com/MUCHIEBERRY/DataHabit
Keywords: behavior-analysis,productivity,student-habits,task-difficulty
Requires-Python: >=3.10
License-File: LICENSE
Requires-Dist: pandas
Requires-Dist: numpy
Dynamic: license-file
